datadog_cdk_constructs_v2/__init__.py
datadog_cdk_constructs_v2/py.typed
datadog_cdk_constructs_v2/_jsii/__init__.py
datadog_cdk_constructs_v2/_jsii/datadog-cdk-constructs-v2@3.8.0.jsii.tgz
datadog_cdk_constructs_v2-3.8.0.dist-info/LICENSE
datadog_cdk_constructs_v2-3.8.0.dist-info/METADATA
datadog_cdk_constructs_v2-3.8.0.dist-info/NOTICE
datadog_cdk_constructs_v2-3.8.0.dist-info/WHEEL
datadog_cdk_constructs_v2-3.8.0.dist-info/top_level.txt
datadog_cdk_constructs_v2-3.8.0.dist-info/RECORD
