Metadata-Version: 2.1
Name: datadog-cdk-constructs-v2
Version: 3.8.0
Summary: CDK Construct Library to automatically instrument Python and Node Lambda functions with Datadog using AWS CDK v2
Home-page: https://github.com/DataDog/datadog-cdk-constructs
Author: Datadog
License: Apache-2.0
Project-URL: Source, https://github.com/DataDog/datadog-cdk-constructs
Classifier: Intended Audience :: Developers
Classifier: Operating System :: OS Independent
Classifier: Programming Language :: JavaScript
Classifier: Programming Language :: Python :: 3 :: Only
Classifier: Programming Language :: Python :: 3.9
Classifier: Programming Language :: Python :: 3.10
Classifier: Programming Language :: Python :: 3.11
Classifier: Typing :: Typed
Classifier: Development Status :: 5 - Production/Stable
Classifier: License :: OSI Approved
Requires-Python: ~=3.9
License-File: LICENSE
License-File: NOTICE
Requires-Dist: aws-cdk-lib <3.0.0,>=2.233.0
Requires-Dist: constructs <11.0.0,>=10.0.5
Requires-Dist: jsii <2.0.0,>=1.125.0
Requires-Dist: publication >=0.0.3
Requires-Dist: typeguard ==2.13.3
